rlbidder/__init__.py
rlbidder/constants.py
rlbidder/py.typed
rlbidder/utils.py
rlbidder/agents/__init__.py
rlbidder/agents/base.py
rlbidder/agents/bc.py
rlbidder/agents/budget_pacer.py
rlbidder/agents/constant_bid.py
rlbidder/agents/cql.py
rlbidder/agents/dt.py
rlbidder/agents/fixed_cpa.py
rlbidder/agents/gas.py
rlbidder/agents/gave.py
rlbidder/agents/get_baseline_agent_configs.py
rlbidder/agents/iql.py
rlbidder/agents/pid.py
rlbidder/agents/stochastic_cpa.py
rlbidder/agents/value_scaled_cpa.py
rlbidder/data/__init__.py
rlbidder/data/data_module.py
rlbidder/data/io.py
rlbidder/data/preprocess.py
rlbidder/data/replay_buffer.py
rlbidder/data/scalers.py
rlbidder/data/traj_dataset.py
rlbidder/envs/__init__.py
rlbidder/envs/sampler.py
rlbidder/envs/simulator.py
rlbidder/evaluation/__init__.py
rlbidder/evaluation/history.py
rlbidder/evaluation/online.py
rlbidder/evaluation/parallel.py
rlbidder/evaluation/summarize.py
rlbidder/evaluation/utils.py
rlbidder/models/__init__.py
rlbidder/models/distributions.py
rlbidder/models/losses.py
rlbidder/models/networks.py
rlbidder/models/optim.py
rlbidder/models/transformers.py
rlbidder/models/utils.py
rlbidder/viz/__init__.py
rlbidder/viz/market_metrics.py
rlbidder/viz/plots.py
rlbidder-0.1.0.dist-info/licenses/LICENSE
rlbidder-0.1.0.dist-info/METADATA
rlbidder-0.1.0.dist-info/WHEEL
rlbidder-0.1.0.dist-info/top_level.txt
rlbidder-0.1.0.dist-info/RECORD
