Metadata-Version: 2.4
Name: rlbidder
Version: 0.1.0
Summary: A modern, modular RL library for auto-bidding in online advertising auctions.
Author: Xingdong Zuo
License-Expression: MIT
Project-URL: Homepage, https://github.com/zuoxingdong/rlbidder
Project-URL: Repository, https://github.com/zuoxingdong/rlbidder
Project-URL: Issues, https://github.com/zuoxingdong/rlbidder/issues
Keywords: reinforcement-learning,autobidding,advertising,auctions,pytorch,offline-rl,rl
Classifier: Development Status :: 3 - Alpha
Classifier: Intended Audience :: Science/Research
Classifier: Intended Audience :: Developers
Classifier: Operating System :: OS Independent
Classifier: Operating System :: POSIX :: Linux
Classifier: Programming Language :: Python :: 3
Classifier: Programming Language :: Python :: 3 :: Only
Classifier: Programming Language :: Python :: 3.11
Classifier: Programming Language :: Python :: 3.12
Classifier: Programming Language :: Python :: 3.13
Classifier: Topic :: Scientific/Engineering :: Artificial Intelligence
Requires-Python: >=3.11
License-File: LICENSE
Requires-Dist: numpy>=1.26
Requires-Dist: torch>=2.6
Requires-Dist: lightning>=2.4
Requires-Dist: polars>=1.6
Requires-Dist: pandas>=2.2
Requires-Dist: scikit-learn>=1.3
Requires-Dist: scipy>=1.11
Requires-Dist: joblib>=1.3
Requires-Dist: tqdm>=4.66
Requires-Dist: rich>=10.2.2
Requires-Dist: plotly>=5.18
Requires-Dist: rliable>=1.0.6
Requires-Dist: aim>=3.17
Requires-Dist: draccus>=0.8
Provides-Extra: dev
Requires-Dist: ruff>=0.5; extra == "dev"
Requires-Dist: black>=24.0; extra == "dev"
Requires-Dist: mypy>=1.10; extra == "dev"
Requires-Dist: pytest>=8.2; extra == "dev"
Requires-Dist: pytest-cov>=5.0; extra == "dev"
Requires-Dist: pytest-xdist>=3.6; extra == "dev"
Requires-Dist: pre-commit>=3.7; extra == "dev"
Requires-Dist: build>=1.2; extra == "dev"
Requires-Dist: twine>=5.0; extra == "dev"
Provides-Extra: docs
Requires-Dist: mkdocs>=1.6; extra == "docs"
Requires-Dist: mkdocs-material>=9.5; extra == "docs"
Requires-Dist: mkdocstrings>=0.25; extra == "docs"
Requires-Dist: mkdocstrings-python>=1.10; extra == "docs"
Requires-Dist: pymdown-extensions>=10.8; extra == "docs"
Provides-Extra: train
Requires-Dist: lightning>=2.4; extra == "train"
Requires-Dist: aim>=3.17; extra == "train"
Requires-Dist: wandb>=0.17; extra == "train"
Requires-Dist: hydra-core>=1.3; extra == "train"
Requires-Dist: draccus>=0.8; extra == "train"
Provides-Extra: eval
Requires-Dist: plotly>=5.18; extra == "eval"
Requires-Dist: rliable>=1.0.6; extra == "eval"
Requires-Dist: pandas>=2.2; extra == "eval"
Provides-Extra: test
Requires-Dist: pytest>=8.2; extra == "test"
Requires-Dist: pytest-cov>=5.0; extra == "test"
Requires-Dist: pytest-xdist>=3.6; extra == "test"
Provides-Extra: all
Requires-Dist: rlbidder[dev,docs,eval,test,train]; extra == "all"
Dynamic: license-file
